test_pkg/__init__.py
test_pkg/somebody.py
test_pkg_yangrenchao-0.1.0.dist-info/LICENSE
test_pkg_yangrenchao-0.1.0.dist-info/METADATA
test_pkg_yangrenchao-0.1.0.dist-info/WHEEL
test_pkg_yangrenchao-0.1.0.dist-info/top_level.txt
test_pkg_yangrenchao-0.1.0.dist-info/RECORD
