Metadata-Version: 2.1
Name: test-pkg-yangrenchao
Version: 0.1.0
Summary: An example for PY84 Courses
Home-page: https://github.com/somebody/sampleproject
Author: Somebody
Author-email: somebody@python123.io
License: UNKNOWN
Platform: UNKNOWN
Classifier: Programming Language :: Python :: 3
Classifier: License :: OSI Approved :: MIT License
Classifier: Operating System :: OS Independent
